cdb_euci/__init__.py
cdb_euci/generate_id.py
cdb_euci-0.0.2.dist-info/LICENSE
cdb_euci-0.0.2.dist-info/METADATA
cdb_euci-0.0.2.dist-info/WHEEL
cdb_euci-0.0.2.dist-info/top_level.txt
cdb_euci-0.0.2.dist-info/RECORD
