Metadata-Version: 2.1
Name: cdb-euci
Version: 0.0.2
Summary: CDB Utils By Euci
Home-page: UNKNOWN
Author: moda
Author-email: 2586935358@qq.com
License: MIT License
Platform: all
Classifier: Intended Audience :: Developers
Classifier: Operating System :: OS Independent
Classifier: Natural Language :: Chinese (Simplified)
Classifier: Programming Language :: Python :: 2.7
Classifier: Programming Language :: Python :: 3
Classifier: License :: OSI Approved :: MIT License
Classifier: Topic :: Software Development :: Libraries
